sscli.py
sssdk.py
shadowsocks_sdk-0.1.0.dev0.dist-info/DESCRIPTION.rst
shadowsocks_sdk-0.1.0.dev0.dist-info/METADATA
shadowsocks_sdk-0.1.0.dev0.dist-info/RECORD
shadowsocks_sdk-0.1.0.dev0.dist-info/WHEEL
shadowsocks_sdk-0.1.0.dev0.dist-info/entry_points.txt
shadowsocks_sdk-0.1.0.dev0.dist-info/metadata.json
shadowsocks_sdk-0.1.0.dev0.dist-info/top_level.txt
