Metadata-Version: 2.0
Name: shadowsocks-sdk
Version: 0.1.0.dev0
Summary: shadowsocks sdk and cli
Home-page: https://github.com/zhengxiaowai/shadowsocks-sdk
Author: zhengxiaowai
Author-email: h1x2y3awalm@gmail.com
License: MIT
Keywords: shadowsocks cli sdk
Platform: UNKNOWN
Classifier: Development Status :: 4 - Beta
Classifier: Environment :: Console
Classifier: License :: OSI Approved :: MIT License
Classifier: Natural Language :: English
Classifier: Operating System :: MacOS
Classifier: Operating System :: Microsoft
Classifier: Operating System :: POSIX :: Linux
Classifier: Programming Language :: Python :: 2
Classifier: Programming Language :: Python :: 3
Classifier: Topic :: Utilities
Classifier: Topic :: System
